django_cards_admin/__init__.py
django_cards_admin/admin.py
django_cards_admin/apps.py
django_cards_admin/models.py
django_cards_admin/tests.py
django_cards_admin/views.py
django_cards_admin/migrations/__init__.py
django_cards_admin/static/admin/css/result-cards.css
django_cards_admin/templates/admin/change_list.html
django_cards_admin/templates/admin/result-card-body.html
django_cards_admin/templates/admin/result-card-footer.html
django_cards_admin/templates/admin/result-card-title.html
django_cards_admin-0.3.3.dist-info/licenses/LICENSE
django_cards_admin-0.3.3.dist-info/METADATA
django_cards_admin-0.3.3.dist-info/WHEEL
django_cards_admin-0.3.3.dist-info/top_level.txt
django_cards_admin-0.3.3.dist-info/RECORD
