Metadata-Version: 2.4
Name: django-cards-admin
Version: 0.3.3
Summary: Show cards in changelist instead of table for django admin site.
Author: rRR0VrFP
Maintainer: rRR0VrFP
License: MIT
Keywords: django admin extentions,django cards admin
Classifier: Development Status :: 5 - Production/Stable
Classifier: Intended Audience :: Developers
Classifier: Topic :: Software Development :: Libraries :: Python Modules
Classifier: License :: OSI Approved :: MIT License
Classifier: Programming Language :: Python :: 3
Classifier: Programming Language :: Python :: 3 :: Only
License-File: LICENSE
Requires-Dist: django
Requires-Dist: django-simple-tags>=0.4.0
Dynamic: author
Dynamic: classifier
Dynamic: description
Dynamic: description-content-type
Dynamic: keywords
Dynamic: license
Dynamic: license-file
Dynamic: maintainer
Dynamic: requires-dist
Dynamic: summary
